<?xml version="1.0" encoding="utf-8"?>
<odoo>
    <record id="res_users_access_right_button" model="ir.ui.view">
        <field name="name">res.users.access.right.view.form.inherit</field>
        <field name="model">res.users</field>
        <field name="inherit_id" ref="base.view_users_form" />
        <field name="arch" type="xml">
            <xpath expr="//div[@name='button_box']" position="inside">
                <button name="action_show_groups" type="object" groups="base.group_no_one"
                    class="oe_stat_button" icon="fa-users">
                    <field string="Groups" name="groups_count" widget="statinfo" />
                </button>
                <button name="action_show_accesses" type="object" groups="base.group_no_one"
                    class="oe_stat_button" icon="fa-list">
                    <field string="Access Rights" name="accesses_count" widget="statinfo" />
                </button>
                <button name="action_show_rules" type="object" groups="base.group_no_one"
                    class="oe_stat_button" icon="fa-list-ul">
                    <field string="Record Rules" name="rules_count" widget="statinfo" />
                </button>
            </xpath>
        </field>
    </record>
</odoo>